alpaca_ccxt/__init__.py
alpaca_ccxt/aax.py
alpaca_ccxt/alpaca.py
alpaca_ccxt/ascendex.py
alpaca_ccxt/bequant.py
alpaca_ccxt/bibox.py
alpaca_ccxt/bigone.py
alpaca_ccxt/binance.py
alpaca_ccxt/binancecoinm.py
alpaca_ccxt/binanceus.py
alpaca_ccxt/binanceusdm.py
alpaca_ccxt/bit2c.py
alpaca_ccxt/bitbank.py
alpaca_ccxt/bitbay.py
alpaca_ccxt/bitbns.py
alpaca_ccxt/bitcoincom.py
alpaca_ccxt/bitfinex.py
alpaca_ccxt/bitfinex2.py
alpaca_ccxt/bitflyer.py
alpaca_ccxt/bitforex.py
alpaca_ccxt/bitget.py
alpaca_ccxt/bithumb.py
alpaca_ccxt/bitmart.py
alpaca_ccxt/bitmex.py
alpaca_ccxt/bitopro.py
alpaca_ccxt/bitpanda.py
alpaca_ccxt/bitrue.py
alpaca_ccxt/bitso.py
alpaca_ccxt/bitstamp.py
alpaca_ccxt/bitstamp1.py
alpaca_ccxt/bittrex.py
alpaca_ccxt/bitvavo.py
alpaca_ccxt/bkex.py
alpaca_ccxt/bl3p.py
alpaca_ccxt/blockchaincom.py
alpaca_ccxt/btcalpha.py
alpaca_ccxt/btcbox.py
alpaca_ccxt/btcmarkets.py
alpaca_ccxt/btctradeua.py
alpaca_ccxt/btcturk.py
alpaca_ccxt/buda.py
alpaca_ccxt/bw.py
alpaca_ccxt/bybit.py
alpaca_ccxt/bytetrade.py
alpaca_ccxt/cdax.py
alpaca_ccxt/cex.py
alpaca_ccxt/coinbase.py
alpaca_ccxt/coinbaseprime.py
alpaca_ccxt/coinbasepro.py
alpaca_ccxt/coincheck.py
alpaca_ccxt/coinex.py
alpaca_ccxt/coinfalcon.py
alpaca_ccxt/coinmate.py
alpaca_ccxt/coinone.py
alpaca_ccxt/coinspot.py
alpaca_ccxt/crex24.py
alpaca_ccxt/cryptocom.py
alpaca_ccxt/currencycom.py
alpaca_ccxt/delta.py
alpaca_ccxt/deribit.py
alpaca_ccxt/digifinex.py
alpaca_ccxt/eqonex.py
alpaca_ccxt/exmo.py
alpaca_ccxt/flowbtc.py
alpaca_ccxt/fmfwio.py
alpaca_ccxt/ftx.py
alpaca_ccxt/ftxus.py
alpaca_ccxt/gateio.py
alpaca_ccxt/gemini.py
alpaca_ccxt/hitbtc.py
alpaca_ccxt/hitbtc3.py
alpaca_ccxt/hollaex.py
alpaca_ccxt/huobi.py
alpaca_ccxt/huobijp.py
alpaca_ccxt/huobipro.py
alpaca_ccxt/idex.py
alpaca_ccxt/independentreserve.py
alpaca_ccxt/indodax.py
alpaca_ccxt/itbit.py
alpaca_ccxt/kraken.py
alpaca_ccxt/kucoin.py
alpaca_ccxt/kucoinfutures.py
alpaca_ccxt/kuna.py
alpaca_ccxt/latoken.py
alpaca_ccxt/lbank.py
alpaca_ccxt/liquid.py
alpaca_ccxt-1.0.2.dist-info/LICENSE.txt
alpaca_ccxt-1.0.2.dist-info/METADATA
alpaca_ccxt-1.0.2.dist-info/WHEEL
alpaca_ccxt-1.0.2.dist-info/top_level.txt
alpaca_ccxt-1.0.2.dist-info/RECORD
