Metadata-Version: 2.1
Name: alpaca-ccxt
Version: 1.0.2
Summary: Alpaca Exchange on CCXT
Home-page: https://ccxt.com
Author: Igor Kroitor
Author-email: igor.kroitor@gmail.com
License: MIT
Project-URL: Funding, https://opencollective.com/ccxt
Project-URL: Twitter, https://twitter.com/ccxt_official
Project-URL: Documentation, https://docs.ccxt.com/en/latest/manual.html
Project-URL: Homepage, https://ccxt.com
Project-URL: Discord, https://discord.gg/ccxt
Keywords: algorithmic,algotrading,altcoin,altcoins,api,arbitrage,real-time,realtime,backtest,backtesting,bitcoin,bot,btc,cny,coin,coins,crypto,cryptocurrency,crypto currency,crypto market,currency,currencies,darkcoin,dash,digital currency,doge,dogecoin,e-commerce,etc,eth,ether,ethereum,exchange,exchanges,eur,framework,invest,investing,investor,library,light,litecoin,ltc,market,market data,markets,merchandise,merchant,minimal,ohlcv,order,orderbook,order book,price,price data,pricefeed,private,pub
Platform: UNKNOWN
Classifier: Development Status :: 4 - Beta
Classifier: Intended Audience :: Developers
Classifier: Intended Audience :: Financial and Insurance Industry
Classifier: Intended Audience :: Information Technology
Classifier: Topic :: Software Development :: Build Tools
Classifier: Topic :: Office/Business :: Financial :: Investment
Classifier: License :: OSI Approved :: MIT License
Classifier: Programming Language :: Python :: 2
Classifier: Programming Language :: Python :: 2.7
Classifier: Programming Language :: Python :: 3
Classifier: Programming Language :: Python :: 3.6
Classifier: Programming Language :: Python :: 3.7
Classifier: Programming Language :: Python :: 3.8
Classifier: Programming Language :: Python :: 3.9
Classifier: Programming Language :: JavaScript
Classifier: Programming Language :: PHP
Classifier: Operating System :: OS Independent
Classifier: Environment :: Console
Requires-Dist: setuptools (>=60.9.0)
Requires-Dist: certifi (>=2018.1.18)
Requires-Dist: requests (>=2.18.4)
Requires-Dist: cryptography (>=2.6.1)
Requires-Dist: aiohttp (>=3.8) ; python_version>="3.5.2"
Requires-Dist: aiodns (>=1.1.1) ; python_version>="3.5.2"
Requires-Dist: yarl (==1.7.2) ; python_version>="3.5.2"
Provides-Extra: doc
Requires-Dist: Sphinx (==4.0) ; extra == 'doc'
Requires-Dist: mistune (==0.8.4) ; extra == 'doc'
Requires-Dist: m2r2 (==0.2.7) ; extra == 'doc'
Requires-Dist: sphinx-rtd-theme (==0.5.2) ; extra == 'doc'
Requires-Dist: readthedocs-sphinx-search (==0.1.0) ; extra == 'doc'
Provides-Extra: qa
Requires-Dist: flake8 (==3.7.9) ; extra == 'qa'
